pypws/__init__.py
pypws/calculations.py
pypws/constants.py
pypws/entities.py
pypws/entity_schemas.py
pypws/enums.py
pypws/materials.py
pypws/utilities.py
pypws-4.2.25.dist-info/METADATA
pypws-4.2.25.dist-info/WHEEL
pypws-4.2.25.dist-info/licenses/LICENSE
pypws-4.2.25.dist-info/RECORD
