Metadata-Version: 2.4
Name: pypws
Version: 4.2.25
Summary: Python library supporting Phast Web Services
Project-URL: Homepage, https://plantwebservices.dnv.com
Project-URL: Phast Desktop, https://www.dnv.com/software/services/plant/consequence-analysis.html
Project-URL: Reference help, https://pwsassets.blob.core.windows.net/prod/PyPws.pdf
Author-email: DNV <software.support@dnv.com>
License-File: LICENSE
Keywords: CPQRA,Consequence Analysis,DNV,Discharge,Dispersion,Explosion,Fire,Flammable,Gas,Hazard,Phast,QRA,Toxic
Classifier: License :: OSI Approved :: MIT License
Classifier: Operating System :: OS Independent
Classifier: Programming Language :: Python :: 3
Requires-Python: >=3.11
Requires-Dist: marshmallow-enum>=1.5.1
Requires-Dist: marshmallow>=4.0.1
Requires-Dist: pyjwt>=2.8.0
Requires-Dist: requests>=2.28.1
Requires-Dist: urllib3>=2.2.2
